ai_object_detection.py
ai_object_detection/__init__.py
ai_object_detection/__main__.py
ai_object_detection/libexcel.py
ai_object_detection/libimageprocessor.py
ai_object_detection/libselenium.py
ai_object_detection-1.1.7.dist-info/LICENSE
ai_object_detection-1.1.7.dist-info/METADATA
ai_object_detection-1.1.7.dist-info/WHEEL
ai_object_detection-1.1.7.dist-info/top_level.txt
ai_object_detection-1.1.7.dist-info/RECORD
