Metadata-Version: 2.1
Name: ai-object-detection
Version: 1.1.7
Summary: AI Object Detection
Home-page: https://github.com/nhanvpt102/AI-Object-Detection
Author: Nhan Vo
Author-email: nhanvpt102@gmail.com
License: MIT
Keywords: AI-Object-Detection
Platform: UNKNOWN
Classifier: Development Status :: 3 - Alpha
Classifier: Intended Audience :: Developers
Classifier: License :: OSI Approved :: MIT License
Classifier: Programming Language :: Python :: 3
Classifier: Programming Language :: Python :: 3.4
Classifier: Programming Language :: Python :: 3.5
Classifier: Programming Language :: Python :: 3.6
Classifier: Programming Language :: Python :: 3.7
Requires-Python: >=3.6
Requires-Dist: selenium
Requires-Dist: openpyxl
Requires-Dist: argparse
Requires-Dist: opencv-python
Requires-Dist: scipy
Requires-Dist: pillow
Requires-Dist: pandas
Requires-Dist: colorlog
Requires-Dist: olefile
Requires-Dist: pdf2image
Requires-Dist: pywin32
Requires-Dist: pypiwin32
Requires-Dist: importlib-resources
